server.py
compiler_explorer_mcp-0.1.3.dist-info/METADATA
compiler_explorer_mcp-0.1.3.dist-info/WHEEL
compiler_explorer_mcp-0.1.3.dist-info/entry_points.txt
compiler_explorer_mcp-0.1.3.dist-info/RECORD
